shiftmanager/__init__.py
shiftmanager/__init__.pyc
shiftmanager/memoized_property.py
shiftmanager/memoized_property.pyc
shiftmanager/metadata.py
shiftmanager/metadata.pyc
shiftmanager/privileges.py
shiftmanager/privileges.pyc
shiftmanager/queries.py
shiftmanager/queries.pyc
shiftmanager/redshift.py
shiftmanager/redshift.pyc
shiftmanager/util.py
shiftmanager/util.pyc
shiftmanager/__pycache__/__init__.cpython-36.pyc
shiftmanager/__pycache__/memoized_property.cpython-36.pyc
shiftmanager/__pycache__/metadata.cpython-36.pyc
shiftmanager/__pycache__/privileges.cpython-36.pyc
shiftmanager/__pycache__/queries.cpython-36.pyc
shiftmanager/__pycache__/redshift.cpython-36.pyc
shiftmanager/__pycache__/util.cpython-36.pyc
shiftmanager/mixins/__init__.py
shiftmanager/mixins/__init__.pyc
shiftmanager/mixins/admin.py
shiftmanager/mixins/admin.pyc
shiftmanager/mixins/postgres.py
shiftmanager/mixins/postgres.pyc
shiftmanager/mixins/reflection.py
shiftmanager/mixins/reflection.pyc
shiftmanager/mixins/s3.py
shiftmanager/mixins/s3.pyc
shiftmanager/mixins/__pycache__/__init__.cpython-36.pyc
shiftmanager/mixins/__pycache__/admin.cpython-36.pyc
shiftmanager/mixins/__pycache__/postgres.cpython-36.pyc
shiftmanager/mixins/__pycache__/reflection.cpython-36.pyc
shiftmanager/mixins/__pycache__/s3.cpython-36.pyc
shiftmanager-0.7.1.dist-info/METADATA
shiftmanager-0.7.1.dist-info/RECORD
shiftmanager-0.7.1.dist-info/WHEEL
shiftmanager-0.7.1.dist-info/top_level.txt
