Metadata-Version: 2.1
Name: shiftmanager
Version: 0.7.1
Summary: Management tools for Amazon Redshift
Home-page: https://shiftmanager.readthedocs.org
Author: Jeff Klukas
Author-email: klukas@simple.com
Maintainer: Jeff Klukas
Maintainer-email: klukas@simple.com
License: UNKNOWN
Platform: UNKNOWN
Classifier: License :: OSI Approved :: BSD License
Classifier: Development Status :: 4 - Beta
Classifier: Programming Language :: Python
Classifier: Programming Language :: Python :: 2
Classifier: Programming Language :: Python :: 2.7
Classifier: Programming Language :: Python :: 3
Classifier: Programming Language :: Python :: 3.3
Classifier: Programming Language :: Python :: 3.4
Classifier: Programming Language :: Python :: 3.5
Classifier: Programming Language :: Python :: 3.6
Classifier: Programming Language :: Python :: Implementation :: PyPy
Requires-Dist: boto (>=2.38.0)
Requires-Dist: psycopg2 (>=2.5.4)
Requires-Dist: sqlalchemy-redshift (>=0.7.0)
Requires-Dist: sqlalchemy-views (>=0.2)
